parallelpipe.py
parallelpipe-0.3.1.dist-info/licenses/LICENSE
parallelpipe-0.3.1.dist-info/METADATA
parallelpipe-0.3.1.dist-info/WHEEL
parallelpipe-0.3.1.dist-info/top_level.txt
parallelpipe-0.3.1.dist-info/RECORD
